disiple/__init__.py
disiple/animations.py
disiple/bokeh_audio_tools.py
disiple/functional.py
disiple/operations.py
disiple/signals.py
disiple/tf_rep.py
disiple/util.py
disiple-0.7.2.dist-info/LICENSE
disiple-0.7.2.dist-info/WHEEL
disiple-0.7.2.dist-info/METADATA
disiple-0.7.2.dist-info/RECORD
