Metadata-Version: 2.1
Name: disiple
Version: 0.7.2
Summary: A lightweight package aimed at teaching DSP with Jupyter Notebooks
Author-email: Johan Pauwels <johan.pauwels@gmail.com>
Requires-Python: >=3.8
Classifier: License :: OSI Approved :: Apache Software License
Requires-Dist: numpy >=1.19.5,<2
Requires-Dist: scipy >=1.6.0,<2
Requires-Dist: bokeh >=3.2,<4
Requires-Dist: matplotlib >=3.2.2,<4
Requires-Dist: miniaudio >=1.46,<2
Requires-Dist: soundcard >=0.4.1
Project-URL: Home, https://github.com/jpauwels/disiple
